<?xml version = '1.0' encoding = 'UTF-8' standalone = 'yes'?>
<jazn-data xmlns:xsi="http://www.w3.org/2001/XMLSchema-instance"
           xsi:noNamespaceSchemaLocation="http://xmlns.oracle.com/oracleas/schema/jazn-data-11_0.xsd">
  <jazn-realm default="jazn.com">
    <realm>
      <name>jazn.com</name>
      <users>
        <user>
          <name>BUYER</name>
          <description>welcome1</description>
          <credentials>{903}QsEF+dwt0a/LXw/MMJbUf226vsmrL/Wa</credentials>
        </user>
        <user>
          <name>aipdt</name>
          <display-name>aipdt</display-name>
          <description>aipdt123</description>
          <credentials>{903}l2M+cAtdENRkUz1V9obSyQd+bQENLRi2</credentials>
        </user>
        <user>
          <name>ndm_admin</name>
          <credentials>{903}jdmCTZUauGBB+ujTzyjBjgo/vdasvQQzbQSSGVQUIfM=</credentials>
          <display-name>ndm_admin</display-name>
        </user>
        <user>
          <name>ndm_planner</name>
          <credentials>{903}swDAUulHFPfx7RQLdDcBxt6YjcBqBft+sG3JIXw7c/0=</credentials>
          <display-name>ndm_planner</display-name>
        </user>
      </users>
      <roles>
        <role>
          <name>Employee</name>
          <display-name>Employee</display-name>
          <members>
            <member>
              <type>user</type>
              <name>BUYER</name>
            </member>
            <member>
              <type>user</type>
              <name>aipdt</name>
            </member>
          </members>
        </role>
        <role>
          <name>Manager</name>
          <display-name>Manager</display-name>
          <members>
            <member>
              <type>user</type>
              <name>aipdt</name>
            </member>
          </members>
        </role>
        <role>
          <name>NDMAdmin</name>
          <display-name>NDM Admin</display-name>
          <description>NDM Admin Enterprise Role</description>
          <members>
            <member>
              <type>user</type>
              <name>aipdt</name>
            </member>
            <member>
              <type>user</type>
              <name>ndm_admin</name>
            </member>
          </members>
        </role>
        <role>
          <name>NDMPlanner</name>
          <display-name>NDM Inventory Planner</display-name>
          <description>NDM Inventory Planner Enterprise Role</description>
          <members>
            <member>
              <type>user</type>
              <name>ndm_planner</name>
            </member>
          </members>
        </role>
      </roles>
    </realm>
  </jazn-realm>
  <policy-store>
    <applications>
      <application>
        <name>NDMTool</name>
        <app-roles>
          <app-role>
            <name>EmployeeRole</name>
            <class>oracle.security.jps.service.policystore.ApplicationRole</class>
            <display-name>Employee Role</display-name>
            <members>
              <member>
                <name>Employee</name>
                <class>oracle.security.jps.internal.core.principals.JpsXmlEnterpriseRoleImpl</class>
              </member>
            </members>
          </app-role>
          <app-role>
            <name>ManagerRole</name>
            <class>oracle.security.jps.service.policystore.ApplicationRole</class>
            <display-name>Manager Role</display-name>
            <members>
              <member>
                <name>Manager</name>
                <class>oracle.security.jps.internal.core.principals.JpsXmlEnterpriseRoleImpl</class>
              </member>
            </members>
          </app-role>
          <app-role>
            <name>test-all</name>
            <class>oracle.security.jps.service.policystore.ApplicationRole</class>
            <display-name>test-all</display-name>
            <members>
              <member>
                <name>anonymous-role</name>
                <class>oracle.security.jps.internal.core.principals.JpsAnonymousRoleImpl</class>
              </member>
            </members>
          </app-role>
          <app-role>
            <name>NDMPlannerRole</name>
            <class>oracle.security.jps.service.policystore.ApplicationRole</class>
            <display-name>NDM Inventory Planner Role</display-name>
            <description>NDM Inventory Planner Application Role</description>
            <members>
              <member>
                <name>NDMPlanner</name>
                <class>oracle.security.jps.internal.core.principals.JpsXmlEnterpriseRoleImpl</class>
              </member>
            </members>            
          </app-role>
          <app-role>
            <name>NDMAdminRole</name>
            <class>oracle.security.jps.service.policystore.ApplicationRole</class>
            <display-name>NDM Admin Role</display-name>
            <description>NDM Admin Application Role</description>
            <members>
              <member>
                <name>NDMAdmin</name>
                <class>oracle.security.jps.internal.core.principals.JpsXmlEnterpriseRoleImpl</class>
              </member>
            </members>            
          </app-role>
        </app-roles>
        <jazn-policy>
          <grant>
            <grantee>
              <principals>
                <principal>
                  <name>anonymous-role</name>
                  <class>oracle.security.jps.internal.core.principals.JpsAnonymousRoleImpl</class>
                </principal>
              </principals>
            </grantee>
            <permissions>
              <permission>
                <class>oracle.adf.controller.security.TaskFlowPermission</class>
                <name>/WEB-INF/oracle/retail/apps/framework/uishell/about/flow/AboutFlow.xml#AboutFlow</name>
                <actions>view</actions>
              </permission>
              <permission>
                <class>oracle.adf.controller.security.TaskFlowPermission</class>
                <name>/WEB-INF/oracle/retail/apps/framework/uishell/navigation/contentarea/flow/ContentAreaFlow.xml#ContentAreaFlow</name>
                <actions>view</actions>
              </permission>
              <permission>
                <class>oracle.adf.controller.security.TaskFlowPermission</class>
                <name>/WEB-INF/oracle/retail/apps/framework/uishell/navigation/renderer/flow/ContentLauncherFlow.xml#ContentLauncherFlow</name>
                <actions>view</actions>
              </permission>
              <permission>
                <class>oracle.adf.controller.security.TaskFlowPermission</class>
                <name>/WEB-INF/oracle/retail/apps/framework/uishell/navigation/contentarea/flow/EmptyPageFlow.xml#EmptyPageFlow</name>
                <actions>view</actions>
              </permission>
              <permission>
                <class>oracle.adf.controller.security.TaskFlowPermission</class>
                <name>/WEB-INF/oracle/retail/apps/framework/uishell/globalmenu/flow/GlobalMainMenuFlow.xml#GlobalMainMenuFlow</name>
                <actions>view</actions>
              </permission>
              <permission>
                <class>oracle.adf.controller.security.TaskFlowPermission</class>
                <name>/WEB-INF/oracle/retail/apps/framework/uishell/security/flow/LoginFormFlow.xml#LoginFormFlow</name>
                <actions>view</actions>
              </permission>
              <permission>
                <class>oracle.adf.controller.security.TaskFlowPermission</class>
                <name>/WEB-INF/oracle/retail/apps/framework/uishell/navigation/renderer/flow/NavigationRendererFlow.xml#NavigationRendererFlow</name>
                <actions>view</actions>
              </permission>
              <permission>
                <class>oracle.adf.controller.security.TaskFlowPermission</class>
                <name>/WEB-INF/oracle/retail/apps/framework/uishell/navigationtree/flow/NavigationTreeFlow.xml#NavigationTreeFlow</name>
                <actions>view</actions>
              </permission>
              <permission>
                <class>oracle.adf.controller.security.TaskFlowPermission</class>
                <name>/WEB-INF/oracle/retail/apps/framework/uishell/preferences/publicui/flow/RetailAppsAccessibilityFlow.xml#RetailAppsAccessibilityFlow</name>
                <actions>view</actions>
              </permission>
              <permission>
                <class>oracle.adf.controller.security.TaskFlowPermission</class>
                <name>/WEB-INF/oracle/retail/apps/framework/uishell/navigation/renderer/flow/TaskflowRendererFlow.xml#TaskflowRendererFlow</name>
                <actions>view</actions>
              </permission>
              <permission>
                <class>oracle.adf.controller.security.TaskFlowPermission</class>
                <name>/WEB-INF/oracle/retail/apps/framework/uishell/example/flow/UiShellBasicExampleFlow.xml#UiShellBasicExampleFlow</name>
                <actions>view</actions>
              </permission>
              <permission>
                <class>oracle.adf.controller.security.TaskFlowPermission</class>
                <name>/WEB-INF/oracle/retail/apps/framework/uishell/navigation/renderer/flow/UrlRendererFlow.xml#UrlRendererFlow</name>
                <actions>view</actions>
              </permission>
              <permission>
                <class>oracle.adf.share.security.authorization.RegionPermission</class>
                <name>oracle.retail.apps.framework.uishell.about.page.AboutPageDef</name>
                <actions>view</actions>
              </permission>
              <permission>
                <class>oracle.adf.share.security.authorization.RegionPermission</class>
                <name>oracle.retail.apps.framework.uishell.navigation.contentarea.page.ContentAreaPageDef</name>
                <actions>view</actions>
              </permission>
              <permission>
                <class>oracle.adf.share.security.authorization.RegionPermission</class>
                <name>oracle.retail.apps.framework.uishell.navigation.renderer.page.ContentLauncherPageDef</name>
                <actions>view</actions>
              </permission>
              <permission>
                <class>oracle.adf.share.security.authorization.RegionPermission</class>
                <name>oracle.retail.apps.framework.uishell.navigationtree.page.NavigationTreePageDef</name>
                <actions>view</actions>
              </permission>
              <permission>
                <class>oracle.adf.share.security.authorization.RegionPermission</class>
                <name>oracle.retail.apps.framework.uishell.pagetemplate.RetailPageTemplatePageDef</name>
                <actions>view</actions>
              </permission>
              <permission>
                <class>oracle.adf.share.security.authorization.RegionPermission</class>
                <name>oracle.retail.apps.framework.uishell.example.page.UiShellBasicExamplePageDef</name>
                <actions>view</actions>
              </permission>
              <permission>
                <class>oracle.adf.share.security.authorization.RegionPermission</class>
                <name>oracle.retail.apps.framework.contextawarereport.publicui.page.ViewContextAwareReportPageDef</name>
                <actions>view</actions>
              </permission>
              <permission>
                <class>oracle.adf.share.security.authorization.RegionPermission</class>
                <name>oracle.retail.apps.raf.test.view.uishell.HomePageDef</name>
                <actions>view</actions>
              </permission>
              <permission>
                <class>oracle.adf.share.security.authorization.RegionPermission</class>
                <name>oracle.retail.apps.raf.test.view.uishell.LoginPageDef</name>
                <actions>view</actions>
              </permission>
              <permission>
                <class>oracle.adf.share.security.authorization.RegionPermission</class>
                <name>oracle.retail.apps.raf.test.view.uishell.PreferencesPageDef</name>
                <actions>view</actions>
              </permission>
              <permission>
                <class>oracle.adf.share.security.authorization.RegionPermission</class>
                <name>oracle.retail.apps.raf.test.view.uishell.AboutPageDef</name>
                <actions>view</actions>
              </permission>
              <permission>
                <class>oracle.adf.controller.security.TaskFlowPermission</class>
                <name>/WEB-INF/oracle/retai/apps/aip/employee/flow/CreateEmployeeFlow.xml#CreateEmployeeFlow</name>
                <actions>customize,grant,personalize,view</actions>
              </permission>
              <permission>
                <class>oracle.adf.controller.security.TaskFlowPermission</class>
                <name>/WEB-INF/com/test/search/flow/ExampleTaskFlow.xml#ExampleTaskFlow</name>
                <actions>view</actions>
              </permission>
              <permission>
                <class>oracle.adf.share.security.authorization.RegionPermission</class>
                <name>oracle.retail.apps.aipdt.uishell.AboutPageDef</name>
                <actions>view</actions>
              </permission>
              <permission>
                <class>oracle.adf.share.security.authorization.RegionPermission</class>
                <name>oracle.retail.apps.aipdt.uishell.HomePageDef</name>
                <actions>view</actions>
              </permission>
              <permission>
                <class>oracle.adf.share.security.authorization.RegionPermission</class>
                <name>oracle.retail.apps.aipdt.uishell.LoginPageDef</name>
                <actions>view</actions>
              </permission>
              <permission>
                <class>oracle.adf.share.security.authorization.RegionPermission</class>
                <name>oracle.retail.apps.aipdt.uishell.PreferencesPageDef</name>
                <actions>view</actions>
              </permission>
              <permission>
                <class>oracle.adf.controller.security.TaskFlowPermission</class>
                <name>/WEB-INF/oracle/retail/apps/aipdt/receivingcalendar/publicui/flow/ReceivingCalendarFlow.xml#ReceivingCalendarFlow</name>
                <actions>view</actions>
              </permission>
              <permission>
                <class>oracle.adf.controller.security.TaskFlowPermission</class>
                <name>/WEB-INF/oracle/retail/apps/aipdt/onoffsalesupply/publicui/flow/OnOffSaleSupplyFlow.xml#OnOffSaleSupplyFlow</name>
                <actions>view</actions>
              </permission>
              <permission>
                <class>oracle.adf.share.security.authorization.RegionPermission</class>
                <name>oracle.retail.apps.aipdt.dt.publicui.page.DeploymentTypePageDef</name>
                <actions>view</actions>
              </permission></permissions>
          </grant>
          <grant>
            <grantee>
              <principals>
                <principal>
                  <name>authenticated-role</name>
                  <class>oracle.security.jps.internal.core.principals.JpsAuthenticatedRoleImpl</class>
                </principal>
              </principals>
            </grantee>
            <permissions>
              <permission>
                <class>oracle.adf.controller.security.TaskFlowPermission</class>
                <name>/WEB-INF/oracle/retail/apps/framework/uishell/preferences/publicui/flow/RetailAppsLanguageFlow.xml#RetailAppsLanguageFlow</name>
                <actions>view</actions>
              </permission>
              <permission>
                <class>oracle.adf.controller.security.TaskFlowPermission</class>
                <name>/WEB-INF/oracle/retail/apps/framework/uishell/preferences/publicui/flow/RetailAppsRegionalFlow.xml#RetailAppsRegionalFlow</name>
                <actions>view</actions>
              </permission>
              <permission>
                <class>oracle.adf.controller.security.TaskFlowPermission</class>
                <name>/WEB-INF/oracle/retail/apps/framework/contextawarereport/publicui/flow/ViewContextAwareReportFlow.xml#ViewContextAwareReportFlow</name>
                <actions>view</actions>
              </permission>
              <permission>
                <class>oracle.adf.controller.security.TaskFlowPermission</class>
                <name>/WEB-INF/com/test/search/flow/ExampleSelectManyShuttleFlow.xml#ExampleSelectManyShuttleFlow</name>
                <actions>view</actions>
              </permission>
              <permission>
                <class>oracle.adf.controller.security.TaskFlowPermission</class>
                <name>/WEB-INF/com/test/search/flow/ExampleTaskFlow.xml#ExampleTaskFlow</name>
                <actions>view</actions>
              </permission>
            </permissions>
          </grant>
          <grant>
            <grantee>
              <principals>
                <principal>
                  <name>ManagerRole</name>
                  <class>oracle.security.jps.service.policystore.ApplicationRole</class>
                </principal>
              </principals>
            </grantee>
            <permissions>
              <permission>
                <class>oracle.adf.controller.security.TaskFlowPermission</class>
                <name>/WEB-INF/oracle/retai/apps/aip/employee/flow/CreateEmployeeFlow.xml#CreateEmployeeFlow</name>
                <actions>customize,grant,personalize,view</actions>
              </permission>
              <permission>
                <class>oracle.adf.controller.security.TaskFlowPermission</class>
                <name>/WEB-INF/oracle/retai/apps/aip/employee/flow/SearchEmployeeFlow.xml#SearchEmployeeFlow</name>
                <actions>view</actions>
              </permission>
              <permission>
                <class>oracle.adf.controller.security.TaskFlowPermission</class>
                <name>/WEB-INF/oracle/retai/apps/aip/employee/Search/flow/SearchEmployeeFlow.xml#SearchEmployeeFlow</name>
                <actions>view</actions>
              </permission>
              <permission>
                <class>oracle.adf.share.security.authorization.RegionPermission</class>
                <name>oracle.retai.apps.aip.employee.flow.CreateEmployeeFlow_CreateEmployeeFlow_createInsertPageDef</name>
                <actions>customize,grant,personalize,view</actions>
              </permission>
              <permission>
                <class>oracle.adf.controller.security.TaskFlowPermission</class>
                <name>/WEB-INF/com/test/search/flow/ExampleSelectManyShuttleFlow.xml#ExampleSelectManyShuttleFlow</name>
                <actions>view</actions>
              </permission>
              <permission>
                <class>oracle.adf.controller.security.TaskFlowPermission</class>
                <name>/WEB-INF/com/test/search/flow/ExampleTaskFlow.xml#ExampleTaskFlow</name>
                <actions>view</actions>
              </permission>
            </permissions>
          </grant>
          <grant>
            <grantee>
              <principals>
                <principal>
                  <name>EmployeeRole</name>
                  <class>oracle.security.jps.service.policystore.ApplicationRole</class>
                </principal>
              </principals>
            </grantee>
            <permissions>
              <permission>
                <class>oracle.adf.controller.security.TaskFlowPermission</class>
                <name>/WEB-INF/oracle/retai/apps/aip/employee/flow/SearchEmployeeFlow.xml#SearchEmployeeFlow</name>
                <actions>view</actions>
              </permission>
              <permission>
                <class>oracle.adf.controller.security.TaskFlowPermission</class>
                <name>/WEB-INF/oracle/retai/apps/aip/employee/Search/flow/SearchEmployeeFlow.xml#SearchEmployeeFlow</name>
                <actions>view</actions>
              </permission>
              <permission>
                <class>oracle.adf.controller.security.TaskFlowPermission</class>
                <name>/WEB-INF/com/test/search/flow/ExampleSelectManyShuttleFlow.xml#ExampleSelectManyShuttleFlow</name>
                <actions>view</actions>
              </permission>
            </permissions>
          </grant>
          <grant>
            <grantee>
              <principals>
                <principal>
                  <class>oracle.security.jps.service.policystore.ApplicationRole</class>
                  <name>NDMAdminRole</name>
                </principal>
              </principals>
            </grantee>
            <permissions>
              <permission>
                <class>oracle.adf.controller.security.TaskFlowPermission</class>
                <name>/WEB-INF/oracle/retail/apps/aipdt/list/create/publicui/flow/CreateSupplyChainListFlow.xml#CreateSupplyChainListFlow</name>
                <actions>view</actions>
              </permission>
              <permission>
                <class>oracle.adf.controller.security.TaskFlowPermission</class>
                <name>/WEB-INF/oracle/retail/apps/aipdt/cds/publicui/flow/CrossDockSetupFlow.xml#CrossDockSetupFlow</name>
                <actions>view</actions>
              </permission>
              <permission>
                <class>oracle.adf.controller.security.TaskFlowPermission</class>
                <name>/WEB-INF/oracle/retail/apps/aipdt/dt/publicui/flow/DeploymentTypeFlow.xml#DeploymentTypeFlow</name>
                <actions>view</actions>
              </permission>
              <permission>
                <class>oracle.adf.controller.security.TaskFlowPermission</class>
                <name>/WEB-INF/oracle/retail/apps/aipdt/np/publicui/flow/NetworkPathFlow.xml#NetworkPathFlow</name>
                <actions>view</actions>
              </permission>
              <permission>
                <class>oracle.adf.controller.security.TaskFlowPermission</class>
                <name>/WEB-INF/oracle/retail/apps/aipdt/rc/publicui/flow/ReceivingCalendarFlow.xml#ReceivingCalendarFlow</name>
                <actions>view</actions>
              </permission>
              <permission>
                <class>oracle.adf.controller.security.TaskFlowPermission</class>
                <name>/WEB-INF/oracle/retail/apps/aipdt/list/create/publicui/flow/SupplyChainListCreationFlow.xml#SupplyChainListCreationFlow</name>
                <actions>view</actions>
              </permission>
              <permission>
                <class>oracle.adf.controller.security.TaskFlowPermission</class>
                <name>/WEB-INF/oracle/retail/apps/aipdt/osos/publicui/flow/OnOffSaleSupplyFlow.xml#OnOffSaleSupplyFlow</name>
                <actions>view</actions>
              </permission>
              <permission>
                <class>oracle.adf.controller.security.TaskFlowPermission</class>
                <name>/WEB-INF/oracle/retail/apps/aipdt/rswspm/publicui/flow/RsWhToStPriorityMatrixFlow.xml#WhToStPriorityMatrixFlow</name>
                <actions>view</actions>
              </permission>
              <permission>
                <class>oracle.adf.controller.security.TaskFlowPermission</class>
                <name>/WEB-INF/oracle/retail/apps/aipdt/rswspm/publicui/flow/RsWhToStPriorityMatrixFlow.xml#RsWhToStPriorityMatrixFlow</name>
                <actions>view</actions>
              </permission>
              <permission>
                <class>oracle.adf.controller.security.TaskFlowPermission</class>
                <name>/WEB-INF/oracle/retail/apps/aipdt/list/maintain/publicui/flow/SupplyChainListMaintainFlow.xml#SupplyChainListMaintainFlow</name>
                <actions>view</actions>
              </permission>
              <permission>
                <class>oracle.adf.controller.security.TaskFlowPermission</class>
                <name>/WEB-INF/oracle/retail/apps/aipdt/xdos/publicui/flow/XDOrderScheduleFlow.xml#XDOrderScheduleFlow</name>
                <actions>view</actions>
              </permission>
              <permission>
                <class>oracle.adf.controller.security.TaskFlowPermission</class>
                <name>/WEB-INF/oracle/retail/apps/aipdt/cnpd/publicui/flow/CorporateNonPlanningDaysFlow.xml#CorporateNonPlanningDaysFlow</name>
                <actions>view</actions>
              </permission>
              <permission>
                <class>oracle.adf.controller.security.TaskFlowPermission</class>
                <name>/WEB-INF/oracle/retail/apps/aipdt/rsos/publicui/flow/RsOrderScheduleFlow.xml#RsOrderScheduleFlow</name>
                <actions>view</actions>
              </permission>
            </permissions>
          </grant>
          <grant>
            <grantee>
              <principals>
                <principal>
                  <class>oracle.security.jps.service.policystore.ApplicationRole</class>
                  <name>NDMPlannerRole</name>
                </principal>
              </principals>
            </grantee>
            <permissions>
              <permission>
                <class>oracle.adf.controller.security.TaskFlowPermission</class>
                <name>/WEB-INF/oracle/retail/apps/aipdt/list/create/publicui/flow/CreateSupplyChainListFlow.xml#CreateSupplyChainListFlow</name>
                <actions>view</actions>
              </permission>
              <permission>
                <class>oracle.adf.controller.security.TaskFlowPermission</class>
                <name>/WEB-INF/oracle/retail/apps/aipdt/dt/publicui/flow/DeploymentTypeFlow.xml#DeploymentTypeFlow</name>
                <actions>view</actions>
              </permission>
              <permission>
                <class>oracle.adf.controller.security.TaskFlowPermission</class>
                <name>/WEB-INF/oracle/retail/apps/aipdt/osos/publicui/flow/OnOffSaleSupplyFlow.xml#OnOffSaleSupplyFlow</name>
                <actions>view</actions>
              </permission>
              <permission>
                <class>oracle.adf.controller.security.TaskFlowPermission</class>
                <name>/WEB-INF/oracle/retail/apps/aipdt/list/create/publicui/flow/SupplyChainListCreationFlow.xml#SupplyChainListCreationFlow</name>
                <actions>view</actions>
              </permission></permissions>
          </grant></jazn-policy>
      </application>
    </applications>
  </policy-store>
</jazn-data>
